myforestplot/__init__.py
myforestplot/__version__.py
myforestplot/myforestplot.py
myforestplot-0.1.1.dist-info/METADATA
myforestplot-0.1.1.dist-info/WHEEL
myforestplot-0.1.1.dist-info/top_level.txt
myforestplot-0.1.1.dist-info/RECORD
